<?xml version="1.0" encoding="UTF-8"?>
<search>
<smilrefs id="id521">
<smilref>speechgen0003.smil#tcp9</smilref>
<smilref>speechgen0009.smil#tcp126</smilref>
<smilref>speechgen0013.smil#tcs1</smilref>
<smilref>speechgen0018.smil#tcp239</smilref>
<smilref>speechgen0018.smil#tcp262</smilref>
</smilrefs>
<smilrefs id="id522">
<smilref>speechgen0008.smil#tcp109</smilref>
<smilref>speechgen0020.smil#tcs26</smilref>
</smilrefs>
<smilrefs id="id523">
<smilref>speechgen0003.smil#tcp10</smilref>
<smilref>speechgen0003.smil#tcp16</smilref>
<smilref>speechgen0005.smil#tcp61</smilref>
<smilref>speechgen0011.smil#tcp152</smilref>
<smilref>speechgen0015.smil#tcp208</smilref>
<smilref>speechgen0016.smil#tcs14</smilref>
<smilref>speechgen0018.smil#tcp251</smilref>
<smilref>speechgen0019.smil#tcp283</smilref>
<smilref>speechgen0020.smil#tcs26</smilref>
<smilref>speechgen0022.smil#tcp376</smilref>
<smilref>speechgen0022.smil#tcp382</smilref>
<smilref>speechgen0023.smil#tcs64</smilref>
<smilref>speechgen0025.smil#tcp442</smilref>
<smilref>speechgen0026.smil#tcs83</smilref>
<smilref>speechgen0029.smil#tcs96</smilref>
<smilref>speechgen0032.smil#tcs115</smilref>
<smilref>speechgen0035.smil#tcp627</smilref>
</smilrefs>
<smilrefs id="id525">
<smilref>speechgen0022.smil#tcp371</smilref>
<smilref>speechgen0022.smil#tcp386</smilref>
<smilref>speechgen0031.smil#tcp542</smilref>
<smilref>speechgen0031.smil#tcp544</smilref>
</smilrefs>
<smilrefs id="id526">
<smilref>speechgen0033.smil#tcp582</smilref>
<smilref>speechgen0034.smil#tcp616</smilref>
</smilrefs>
<smilrefs id="id527">
<smilref>speechgen0015.smil#tcp204</smilref>
<smilref>speechgen0018.smil#tcp258</smilref>
<smilref>speechgen0022.smil#tcp389</smilref>
<smilref>speechgen0033.smil#tcp591</smilref>
</smilrefs>
<smilrefs id="id528">
<smilref>speechgen0003.smil#tcp16</smilref>
<smilref>speechgen0004.smil#tcp28</smilref>
<smilref>speechgen0007.smil#tcp84</smilref>
<smilref>speechgen0009.smil#tcp126</smilref>
<smilref>speechgen0010.smil#tcp133</smilref>
<smilref>speechgen0012.smil#tcp163</smilref>
<smilref>speechgen0013.smil#tcp165</smilref>
<smilref>speechgen0013.smil#tcs1</smilref>
<smilref>speechgen0014.smil#tcp195</smilref>
<smilref>speechgen0033.smil#tcp588</smilref>
<smilref>speechgen0035.smil#tcp630</smilref>
</smilrefs>
<smilrefs id="id529">
<smilref>speechgen0004.smil#tcp45</smilref>
<smilref>speechgen0010.smil#tcp131</smilref>
<smilref>speechgen0018.smil#tcp242</smilref>
<smilref>speechgen0018.smil#tcp268</smilref>
<smilref>speechgen0018.smil#tcp273</smilref>
<smilref>speechgen0018.smil#tcp274</smilref>
<smilref>speechgen0020.smil#tcs26</smilref>
<smilref>speechgen0027.smil#tcp479</smilref>
<smilref>speechgen0028.smil#tcp481</smilref>
<smilref>speechgen0028.smil#tcp482</smilref>
<smilref>speechgen0028.smil#tcp483</smilref>
<smilref>speechgen0028.smil#tcp486</smilref>
<smilref>speechgen0028.smil#tcp487</smilref>
<smilref>speechgen0028.smil#tcp491</smilref>
<smilref>speechgen0028.smil#tcp492</smilref>
<smilref>speechgen0028.smil#tcp493</smilref>
<smilref>speechgen0028.smil#tcp494</smilref>
<smilref>speechgen0028.smil#tcp495</smilref>
<smilref>speechgen0028.smil#tcp496</smilref>
<smilref>speechgen0028.smil#tcp497</smilref>
<smilref>speechgen0028.smil#tcp498</smilref>
<smilref>speechgen0028.smil#tcp500</smilref>
<smilref>speechgen0029.smil#tcp501</smilref>
<smilref>speechgen0029.smil#tcs96</smilref>
<smilref>speechgen0030.smil#tcp539</smilref>
<smilref>speechgen0031.smil#tcp541</smilref>
<smilref>speechgen0031.smil#tcp542</smilref>
<smilref>speechgen0031.smil#tcp545</smilref>
<smilref>speechgen0031.smil#tcp546</smilref>
<smilref>speechgen0032.smil#tcp548</smilref>
<smilref>speechgen0032.smil#tcs115</smilref>
<smilref>speechgen0033.smil#tcp588</smilref>
<smilref>speechgen0033.smil#tcp597</smilref>
</smilrefs>
<smilrefs id="id530">
<smilref>speechgen0010.smil#tcp141</smilref>
</smilrefs>
<smilrefs id="id531">
<smilref>speechgen0028.smil#tcp494</smilref>
<smilref>speechgen0029.smil#tcs96</smilref>
</smilrefs>
<smilrefs id="id532">
<smilref>speechgen0028.smil#tcp480</smilref>
</smilrefs>
<smilrefs id="id533">
<smilref>speechgen0010.smil#tcp137</smilref>
<smilref>speechgen0010.smil#tcp141</smilref>
<smilref>speechgen0010.smil#tcp143</smilref>
</smilrefs>
<smilrefs id="id534">
<smilref>speechgen0010.smil#tcp135</smilref>
</smilrefs>
<smilrefs id="id535">
<smilref>speechgen0005.smil#tcp60</smilref>
<smilref>speechgen0005.smil#tcp62</smilref>
<smilref>speechgen0020.smil#tcs26</smilref>
<smilref>speechgen0033.smil#tcp599</smilref>
</smilrefs>
<smilrefs id="id536">
<smilref>speechgen0015.smil#tcp200</smilref>
<smilref>speechgen0018.smil#tcp252</smilref>
<smilref>speechgen0028.smil#tcp487</smilref>
</smilrefs>
<smilrefs id="id537">
<smilref>speechgen0009.smil#tcp127</smilref>
<smilref>speechgen0020.smil#tcs26</smilref>
<smilref>speechgen0028.smil#tcp499</smilref>
</smilrefs>
<smilrefs id="id538">
<smilref>speechgen0011.smil#tcp153</smilref>
<smilref>speechgen0018.smil#tcp257</smilref>
<smilref>speechgen0025.smil#tcp445</smilref>
<smilref>speechgen0028.smil#tcp482</smilref>
<smilref>speechgen0028.smil#tcp491</smilref>
<smilref>speechgen0031.smil#tcp543</smilref>
<smilref>speechgen0033.smil#tcp579</smilref>
<smilref>speechgen0033.smil#tcp581</smilref>
<smilref>speechgen0034.smil#tcp615</smilref>
<smilref>speechgen0038.smil#tcp651</smilref>
</smilrefs>
<smilrefs id="id539">
<smilref>speechgen0013.smil#tcs1</smilref>
<smilref>speechgen0018.smil#tcp271</smilref>
<smilref>speechgen0019.smil#tcp278</smilref>
<smilref>speechgen0019.smil#tcp279</smilref>
<smilref>speechgen0022.smil#tcp374</smilref>
<smilref>speechgen0023.smil#tcs64</smilref>
<smilref>speechgen0026.smil#tcs83</smilref>
<smilref>speechgen0028.smil#tcp491</smilref>
<smilref>speechgen0033.smil#tcp575</smilref>
<smilref>speechgen0034.smil#tcp607</smilref>
</smilrefs>
<smilrefs id="id540">
<smilref>speechgen0028.smil#tcp495</smilref>
</smilrefs>
<smilrefs id="id541">
<smilref>speechgen0015.smil#tcp199</smilref>
<smilref>speechgen0016.smil#tcs14</smilref>
<smilref>speechgen0018.smil#tcp257</smilref>
<smilref>speechgen0018.smil#tcp258</smilref>
</smilrefs>
<smilrefs id="id542">
<smilref>speechgen0029.smil#tcs96</smilref>
</smilrefs>
<smilrefs id="id543">
<smilref>speechgen0037.smil#tcp639</smilref>
</smilrefs>
<smilrefs id="id544">
<smilref>speechgen0037.smil#tcp640</smilref>
</smilrefs>
<smilrefs id="id545">
<smilref>speechgen0007.smil#tcp80</smilref>
</smilrefs>
<smilrefs id="id546">
<smilref>speechgen0022.smil#tcp398</smilref>
<smilref>speechgen0033.smil#tcp599</smilref>
<smilref>speechgen0038.smil#tcp646</smilref>
</smilrefs>
<smilrefs id="id547">
<smilref>speechgen0023.smil#tcs64</smilref>
<smilref>speechgen0029.smil#tcs96</smilref>
</smilrefs>
<smilrefs id="id548">
<smilref>speechgen0003.smil#tcp6</smilref>
</smilrefs>
<smilrefs id="id549">
<smilref>speechgen0022.smil#tcp398</smilref>
<smilref>speechgen0033.smil#tcp574</smilref>
<smilref>speechgen0034.smil#tcp606</smilref>
<smilref>speechgen0038.smil#tcp646</smilref>
</smilrefs>
<smilrefs id="id550">
<smilref>speechgen0033.smil#tcp599</smilref>
</smilrefs>
<smilrefs id="id551">
<smilref>speechgen0004.smil#tcp39</smilref>
<smilref>speechgen0038.smil#tcp647</smilref>
<smilref>speechgen0038.smil#tcp648</smilref>
<smilref>speechgen0038.smil#tcp651</smilref>
<smilref>speechgen0038.smil#tcp655</smilref>
</smilrefs>
<smilrefs id="id552">
<smilref>speechgen0018.smil#tcp260</smilref>
</smilrefs>
<smilrefs id="id553">
<smilref>speechgen0004.smil#tcp26</smilref>
<smilref>speechgen0019.smil#tcp278</smilref>
<smilref>speechgen0033.smil#tcp573</smilref>
<smilref>speechgen0034.smil#tcp605</smilref>
</smilrefs>
<smilrefs id="id554">
<smilref>speechgen0038.smil#tcp654</smilref>
</smilrefs>
<smilrefs id="id555">
<smilref>speechgen0015.smil#tcp200</smilref>
<smilref>speechgen0037.smil#tcp638</smilref>
</smilrefs>
<smilrefs id="id556">
<smilref>speechgen0028.smil#tcp493</smilref>
<smilref>speechgen0031.smil#tcp541</smilref>
<smilref>speechgen0033.smil#tcp583</smilref>
<smilref>speechgen0033.smil#tcp591</smilref>
</smilrefs>
<smilrefs id="id557">
<smilref>speechgen0010.smil#tcp141</smilref>
<smilref>speechgen0028.smil#tcp483</smilref>
<smilref>speechgen0028.smil#tcp490</smilref>
<smilref>speechgen0028.smil#tcp491</smilref>
<smilref>speechgen0028.smil#tcp497</smilref>
</smilrefs>
<smilrefs id="id558">
<smilref>speechgen0004.smil#tcp45</smilref>
</smilrefs>
<smilrefs id="id559">
<smilref>speechgen0007.smil#tcp78</smilref>
</smilrefs>
<smilrefs id="id560">
<smilref>speechgen0015.smil#tcp198</smilref>
</smilrefs>
</search>
