<?xml version="1.0" encoding="UTF-8"?>
<search>
<smilrefs id="id601">
<smilref>speechgen0004.smil#tcp22</smilref>
<smilref>speechgen0004.smil#tcp26</smilref>
<smilref>speechgen0009.smil#tcp124</smilref>
<smilref>speechgen0011.smil#tcp145</smilref>
<smilref>speechgen0013.smil#tcs1</smilref>
<smilref>speechgen0014.smil#tcp195</smilref>
<smilref>speechgen0016.smil#tcs14</smilref>
<smilref>speechgen0018.smil#tcp267</smilref>
<smilref>speechgen0019.smil#tcp278</smilref>
<smilref>speechgen0020.smil#tcs26</smilref>
<smilref>speechgen0022.smil#tcp385</smilref>
<smilref>speechgen0023.smil#tcs64</smilref>
<smilref>speechgen0025.smil#tcp439</smilref>
<smilref>speechgen0026.smil#tcs83</smilref>
<smilref>speechgen0028.smil#tcp491</smilref>
<smilref>speechgen0028.smil#tcp500</smilref>
<smilref>speechgen0031.smil#tcp545</smilref>
<smilref>speechgen0032.smil#tcs115</smilref>
<smilref>speechgen0033.smil#tcp573</smilref>
<smilref>speechgen0033.smil#tcp591</smilref>
<smilref>speechgen0034.smil#tcp605</smilref>
</smilrefs>
<smilrefs id="id602">
<smilref>speechgen0013.smil#tcp165</smilref>
<smilref>speechgen0016.smil#tcp209</smilref>
<smilref>speechgen0020.smil#tcp286</smilref>
<smilref>speechgen0023.smil#tcp399</smilref>
<smilref>speechgen0026.smil#tcp452</smilref>
<smilref>speechgen0029.smil#tcp501</smilref>
<smilref>speechgen0032.smil#tcp548</smilref>
</smilrefs>
<smilrefs id="id603">
<smilref>speechgen0004.smil#tcp25</smilref>
</smilrefs>
<smilrefs id="id604">
<smilref>speechgen0010.smil#tcp142</smilref>
</smilrefs>
<smilrefs id="id605">
<smilref>speechgen0009.smil#tcp125</smilref>
</smilrefs>
<smilrefs id="id606">
<smilref>speechgen0028.smil#tcp486</smilref>
<smilref>speechgen0028.smil#tcp487</smilref>
</smilrefs>
<smilrefs id="id607">
<smilref>speechgen0028.smil#tcp480</smilref>
<smilref>speechgen0028.smil#tcp497</smilref>
</smilrefs>
<smilrefs id="id608">
<smilref>speechgen0008.smil#tcp87</smilref>
<smilref>speechgen0008.smil#tcp89</smilref>
<smilref>speechgen0008.smil#tcp95</smilref>
<smilref>speechgen0008.smil#tcp97</smilref>
<smilref>speechgen0008.smil#tcp99</smilref>
<smilref>speechgen0018.smil#tcp268</smilref>
<smilref>speechgen0019.smil#tcp277</smilref>
<smilref>speechgen0019.smil#tcp278</smilref>
<smilref>speechgen0019.smil#tcp282</smilref>
<smilref>speechgen0022.smil#tcp368</smilref>
<smilref>speechgen0022.smil#tcp369</smilref>
<smilref>speechgen0022.smil#tcp371</smilref>
<smilref>speechgen0022.smil#tcp373</smilref>
<smilref>speechgen0022.smil#tcp374</smilref>
<smilref>speechgen0022.smil#tcp376</smilref>
<smilref>speechgen0022.smil#tcp380</smilref>
<smilref>speechgen0022.smil#tcp381</smilref>
<smilref>speechgen0022.smil#tcp382</smilref>
<smilref>speechgen0022.smil#tcp394</smilref>
<smilref>speechgen0022.smil#tcp397</smilref>
<smilref>speechgen0023.smil#tcs64</smilref>
<smilref>speechgen0028.smil#tcp482</smilref>
<smilref>speechgen0028.smil#tcp484</smilref>
<smilref>speechgen0028.smil#tcp485</smilref>
<smilref>speechgen0028.smil#tcp486</smilref>
<smilref>speechgen0028.smil#tcp490</smilref>
<smilref>speechgen0028.smil#tcp491</smilref>
<smilref>speechgen0029.smil#tcs96</smilref>
<smilref>speechgen0031.smil#tcp543</smilref>
<smilref>speechgen0031.smil#tcp546</smilref>
<smilref>speechgen0032.smil#tcs115</smilref>
<smilref>speechgen0033.smil#tcp575</smilref>
<smilref>speechgen0033.smil#tcp592</smilref>
<smilref>speechgen0033.smil#tcp597</smilref>
<smilref>speechgen0034.smil#tcp607</smilref>
<smilref>speechgen0037.smil#tcp639</smilref>
<smilref>speechgen0038.smil#tcp642</smilref>
<smilref>speechgen0038.smil#tcp645</smilref>
<smilref>speechgen0039.smil#tcp658</smilref>
</smilrefs>
<smilrefs id="id609">
<smilref>speechgen0018.smil#tcp254</smilref>
<smilref>speechgen0028.smil#tcp486</smilref>
</smilrefs>
<smilrefs id="id610">
<smilref>speechgen0010.smil#tcp137</smilref>
<smilref>speechgen0018.smil#tcp259</smilref>
<smilref>speechgen0018.smil#tcp272</smilref>
<smilref>speechgen0028.smil#tcp486</smilref>
<smilref>speechgen0028.smil#tcp487</smilref>
<smilref>speechgen0028.smil#tcp499</smilref>
<smilref>speechgen0033.smil#tcp581</smilref>
<smilref>speechgen0033.smil#tcp583</smilref>
<smilref>speechgen0034.smil#tcp615</smilref>
<smilref>speechgen0034.smil#tcp616</smilref>
<smilref>speechgen0037.smil#tcp637</smilref>
</smilrefs>
<smilrefs id="id611">
<smilref>speechgen0003.smil#tcp5</smilref>
<smilref>speechgen0003.smil#tcp6</smilref>
<smilref>speechgen0003.smil#tcp7</smilref>
<smilref>speechgen0003.smil#tcp8</smilref>
<smilref>speechgen0003.smil#tcp9</smilref>
<smilref>speechgen0003.smil#tcp10</smilref>
<smilref>speechgen0003.smil#tcp11</smilref>
<smilref>speechgen0003.smil#tcp12</smilref>
<smilref>speechgen0003.smil#tcp13</smilref>
<smilref>speechgen0003.smil#tcp14</smilref>
<smilref>speechgen0003.smil#tcp15</smilref>
<smilref>speechgen0003.smil#tcp16</smilref>
<smilref>speechgen0003.smil#tcp18</smilref>
<smilref>speechgen0004.smil#tcp21</smilref>
<smilref>speechgen0004.smil#tcp23</smilref>
<smilref>speechgen0004.smil#tcp24</smilref>
<smilref>speechgen0004.smil#tcp25</smilref>
<smilref>speechgen0004.smil#tcp26</smilref>
<smilref>speechgen0004.smil#tcp35</smilref>
<smilref>speechgen0004.smil#tcp39</smilref>
<smilref>speechgen0005.smil#tcp52</smilref>
<smilref>speechgen0005.smil#tcp63</smilref>
<smilref>speechgen0007.smil#tcp78</smilref>
<smilref>speechgen0009.smil#tcp119</smilref>
<smilref>speechgen0009.smil#tcp120</smilref>
<smilref>speechgen0009.smil#tcp121</smilref>
<smilref>speechgen0009.smil#tcp122</smilref>
<smilref>speechgen0009.smil#tcp123</smilref>
<smilref>speechgen0009.smil#tcp124</smilref>
<smilref>speechgen0009.smil#tcp125</smilref>
<smilref>speechgen0009.smil#tcp126</smilref>
<smilref>speechgen0009.smil#tcp127</smilref>
<smilref>speechgen0010.smil#tcp128</smilref>
<smilref>speechgen0010.smil#tcp129</smilref>
<smilref>speechgen0010.smil#tcp130</smilref>
<smilref>speechgen0010.smil#tcp131</smilref>
<smilref>speechgen0010.smil#tcp132</smilref>
<smilref>speechgen0010.smil#tcp133</smilref>
<smilref>speechgen0010.smil#tcp134</smilref>
<smilref>speechgen0010.smil#tcp135</smilref>
<smilref>speechgen0010.smil#tcp137</smilref>
<smilref>speechgen0010.smil#tcp138</smilref>
<smilref>speechgen0010.smil#tcp139</smilref>
<smilref>speechgen0010.smil#tcp140</smilref>
<smilref>speechgen0010.smil#tcp141</smilref>
<smilref>speechgen0010.smil#tcp142</smilref>
<smilref>speechgen0010.smil#tcp143</smilref>
<smilref>speechgen0011.smil#tcp145</smilref>
<smilref>speechgen0011.smil#tcp146</smilref>
<smilref>speechgen0011.smil#tcp147</smilref>
<smilref>speechgen0011.smil#tcp148</smilref>
<smilref>speechgen0011.smil#tcp149</smilref>
<smilref>speechgen0011.smil#tcp150</smilref>
<smilref>speechgen0011.smil#tcp151</smilref>
<smilref>speechgen0011.smil#tcp152</smilref>
<smilref>speechgen0011.smil#tcp153</smilref>
<smilref>speechgen0011.smil#tcp154</smilref>
<smilref>speechgen0011.smil#tcp156</smilref>
<smilref>speechgen0011.smil#tcp159</smilref>
<smilref>speechgen0012.smil#tcp161</smilref>
<smilref>speechgen0012.smil#tcp162</smilref>
<smilref>speechgen0012.smil#tcp163</smilref>
<smilref>speechgen0012.smil#tcp164</smilref>
<smilref>speechgen0013.smil#tcs1</smilref>
<smilref>speechgen0014.smil#tcp193</smilref>
<smilref>speechgen0014.smil#tcp194</smilref>
<smilref>speechgen0014.smil#tcp195</smilref>
<smilref>speechgen0015.smil#tcp196</smilref>
<smilref>speechgen0015.smil#tcp197</smilref>
<smilref>speechgen0015.smil#tcp198</smilref>
<smilref>speechgen0015.smil#tcp199</smilref>
<smilref>speechgen0015.smil#tcp200</smilref>
<smilref>speechgen0015.smil#tcp201</smilref>
<smilref>speechgen0015.smil#tcp202</smilref>
<smilref>speechgen0015.smil#tcp204</smilref>
<smilref>speechgen0015.smil#tcp205</smilref>
<smilref>speechgen0015.smil#tcp206</smilref>
<smilref>speechgen0015.smil#tcp207</smilref>
<smilref>speechgen0015.smil#tcp208</smilref>
<smilref>speechgen0016.smil#tcs14</smilref>
<smilref>speechgen0018.smil#tcp237</smilref>
<smilref>speechgen0018.smil#tcp238</smilref>
<smilref>speechgen0018.smil#tcp239</smilref>
<smilref>speechgen0018.smil#tcp240</smilref>
<smilref>speechgen0018.smil#tcp241</smilref>
<smilref>speechgen0018.smil#tcp242</smilref>
<smilref>speechgen0018.smil#tcp243</smilref>
<smilref>speechgen0018.smil#tcp244</smilref>
<smilref>speechgen0018.smil#tcp245</smilref>
<smilref>speechgen0018.smil#tcp246</smilref>
<smilref>speechgen0018.smil#tcp247</smilref>
<smilref>speechgen0018.smil#tcp248</smilref>
<smilref>speechgen0018.smil#tcp249</smilref>
<smilref>speechgen0018.smil#tcp250</smilref>
<smilref>speechgen0018.smil#tcp251</smilref>
<smilref>speechgen0018.smil#tcp252</smilref>
<smilref>speechgen0018.smil#tcp255</smilref>
<smilref>speechgen0018.smil#tcp256</smilref>
<smilref>speechgen0018.smil#tcp257</smilref>
<smilref>speechgen0018.smil#tcp258</smilref>
<smilref>speechgen0018.smil#tcp259</smilref>
<smilref>speechgen0018.smil#tcp260</smilref>
<smilref>speechgen0018.smil#tcp261</smilref>
<smilref>speechgen0018.smil#tcp262</smilref>
<smilref>speechgen0018.smil#tcp263</smilref>
<smilref>speechgen0018.smil#tcp264</smilref>
<smilref>speechgen0018.smil#tcp265</smilref>
<smilref>speechgen0018.smil#tcp267</smilref>
<smilref>speechgen0018.smil#tcp268</smilref>
<smilref>speechgen0018.smil#tcp269</smilref>
<smilref>speechgen0018.smil#tcp270</smilref>
<smilref>speechgen0018.smil#tcp273</smilref>
<smilref>speechgen0018.smil#tcp274</smilref>
<smilref>speechgen0019.smil#tcp276</smilref>
<smilref>speechgen0019.smil#tcp277</smilref>
<smilref>speechgen0019.smil#tcp278</smilref>
<smilref>speechgen0019.smil#tcp279</smilref>
<smilref>speechgen0019.smil#tcp280</smilref>
<smilref>speechgen0019.smil#tcp281</smilref>
<smilref>speechgen0019.smil#tcp282</smilref>
<smilref>speechgen0019.smil#tcp283</smilref>
<smilref>speechgen0019.smil#tcp284</smilref>
<smilref>speechgen0019.smil#tcp285</smilref>
<smilref>speechgen0020.smil#tcs26</smilref>
<smilref>speechgen0022.smil#tcp366</smilref>
<smilref>speechgen0022.smil#tcp367</smilref>
<smilref>speechgen0022.smil#tcp369</smilref>
<smilref>speechgen0022.smil#tcp370</smilref>
<smilref>speechgen0022.smil#tcp371</smilref>
<smilref>speechgen0022.smil#tcp372</smilref>
<smilref>speechgen0022.smil#tcp373</smilref>
<smilref>speechgen0022.smil#tcp374</smilref>
<smilref>speechgen0022.smil#tcp375</smilref>
<smilref>speechgen0022.smil#tcp376</smilref>
<smilref>speechgen0022.smil#tcp377</smilref>
<smilref>speechgen0022.smil#tcp378</smilref>
<smilref>speechgen0022.smil#tcp379</smilref>
<smilref>speechgen0022.smil#tcp380</smilref>
<smilref>speechgen0022.smil#tcp381</smilref>
<smilref>speechgen0022.smil#tcp382</smilref>
<smilref>speechgen0022.smil#tcp383</smilref>
<smilref>speechgen0022.smil#tcp384</smilref>
<smilref>speechgen0022.smil#tcp385</smilref>
<smilref>speechgen0022.smil#tcp386</smilref>
<smilref>speechgen0022.smil#tcp387</smilref>
<smilref>speechgen0022.smil#tcp388</smilref>
<smilref>speechgen0022.smil#tcp389</smilref>
<smilref>speechgen0022.smil#tcp390</smilref>
<smilref>speechgen0022.smil#tcp393</smilref>
<smilref>speechgen0022.smil#tcp394</smilref>
<smilref>speechgen0022.smil#tcp395</smilref>
<smilref>speechgen0022.smil#tcp396</smilref>
<smilref>speechgen0022.smil#tcp397</smilref>
<smilref>speechgen0022.smil#tcp398</smilref>
<smilref>speechgen0023.smil#tcs64</smilref>
<smilref>speechgen0025.smil#tcp439</smilref>
<smilref>speechgen0025.smil#tcp440</smilref>
<smilref>speechgen0025.smil#tcp441</smilref>
<smilref>speechgen0025.smil#tcp442</smilref>
<smilref>speechgen0025.smil#tcp443</smilref>
<smilref>speechgen0025.smil#tcp444</smilref>
<smilref>speechgen0025.smil#tcp445</smilref>
<smilref>speechgen0025.smil#tcp446</smilref>
<smilref>speechgen0025.smil#tcp448</smilref>
<smilref>speechgen0025.smil#tcp451</smilref>
<smilref>speechgen0026.smil#tcs83</smilref>
<smilref>speechgen0028.smil#tcp481</smilref>
<smilref>speechgen0028.smil#tcp482</smilref>
<smilref>speechgen0028.smil#tcp486</smilref>
<smilref>speechgen0028.smil#tcp487</smilref>
<smilref>speechgen0028.smil#tcp489</smilref>
<smilref>speechgen0028.smil#tcp491</smilref>
<smilref>speechgen0028.smil#tcp492</smilref>
<smilref>speechgen0028.smil#tcp493</smilref>
<smilref>speechgen0028.smil#tcp494</smilref>
<smilref>speechgen0028.smil#tcp495</smilref>
<smilref>speechgen0028.smil#tcp496</smilref>
<smilref>speechgen0028.smil#tcp497</smilref>
<smilref>speechgen0028.smil#tcp498</smilref>
<smilref>speechgen0028.smil#tcp500</smilref>
<smilref>speechgen0029.smil#tcs96</smilref>
<smilref>speechgen0031.smil#tcp541</smilref>
<smilref>speechgen0031.smil#tcp542</smilref>
<smilref>speechgen0031.smil#tcp543</smilref>
<smilref>speechgen0031.smil#tcp544</smilref>
<smilref>speechgen0031.smil#tcp545</smilref>
<smilref>speechgen0031.smil#tcp546</smilref>
<smilref>speechgen0032.smil#tcs115</smilref>
<smilref>speechgen0033.smil#tcp572</smilref>
<smilref>speechgen0033.smil#tcp573</smilref>
<smilref>speechgen0033.smil#tcp574</smilref>
<smilref>speechgen0033.smil#tcp575</smilref>
<smilref>speechgen0033.smil#tcp576</smilref>
<smilref>speechgen0033.smil#tcp577</smilref>
<smilref>speechgen0033.smil#tcp578</smilref>
<smilref>speechgen0033.smil#tcp579</smilref>
<smilref>speechgen0033.smil#tcp580</smilref>
<smilref>speechgen0033.smil#tcp581</smilref>
<smilref>speechgen0033.smil#tcp582</smilref>
<smilref>speechgen0033.smil#tcp584</smilref>
<smilref>speechgen0033.smil#tcp586</smilref>
<smilref>speechgen0033.smil#tcp588</smilref>
<smilref>speechgen0033.smil#tcp589</smilref>
<smilref>speechgen0033.smil#tcp590</smilref>
<smilref>speechgen0033.smil#tcp591</smilref>
<smilref>speechgen0033.smil#tcp592</smilref>
<smilref>speechgen0033.smil#tcp593</smilref>
<smilref>speechgen0033.smil#tcp594</smilref>
<smilref>speechgen0033.smil#tcp595</smilref>
<smilref>speechgen0033.smil#tcp597</smilref>
<smilref>speechgen0033.smil#tcp599</smilref>
<smilref>speechgen0033.smil#tcp600</smilref>
<smilref>speechgen0034.smil#tcp603</smilref>
<smilref>speechgen0034.smil#tcp604</smilref>
<smilref>speechgen0034.smil#tcp605</smilref>
<smilref>speechgen0034.smil#tcp606</smilref>
<smilref>speechgen0034.smil#tcp607</smilref>
<smilref>speechgen0034.smil#tcp608</smilref>
<smilref>speechgen0034.smil#tcp609</smilref>
<smilref>speechgen0034.smil#tcp610</smilref>
<smilref>speechgen0034.smil#tcp611</smilref>
<smilref>speechgen0034.smil#tcp613</smilref>
<smilref>speechgen0034.smil#tcp614</smilref>
<smilref>speechgen0034.smil#tcp615</smilref>
<smilref>speechgen0034.smil#tcp616</smilref>
<smilref>speechgen0034.smil#tcp617</smilref>
<smilref>speechgen0034.smil#tcp620</smilref>
<smilref>speechgen0034.smil#tcp622</smilref>
<smilref>speechgen0034.smil#tcp623</smilref>
<smilref>speechgen0034.smil#tcp624</smilref>
<smilref>speechgen0035.smil#tcp627</smilref>
<smilref>speechgen0035.smil#tcp628</smilref>
<smilref>speechgen0035.smil#tcp629</smilref>
<smilref>speechgen0035.smil#tcp630</smilref>
<smilref>speechgen0035.smil#tcp631</smilref>
<smilref>speechgen0037.smil#tcp636</smilref>
<smilref>speechgen0037.smil#tcp637</smilref>
<smilref>speechgen0037.smil#tcp638</smilref>
<smilref>speechgen0037.smil#tcp639</smilref>
<smilref>speechgen0037.smil#tcp640</smilref>
<smilref>speechgen0038.smil#tcp642</smilref>
<smilref>speechgen0038.smil#tcp643</smilref>
<smilref>speechgen0038.smil#tcp644</smilref>
<smilref>speechgen0038.smil#tcp645</smilref>
<smilref>speechgen0038.smil#tcp646</smilref>
<smilref>speechgen0038.smil#tcp647</smilref>
<smilref>speechgen0038.smil#tcp648</smilref>
<smilref>speechgen0038.smil#tcp649</smilref>
<smilref>speechgen0038.smil#tcp650</smilref>
<smilref>speechgen0038.smil#tcp651</smilref>
<smilref>speechgen0038.smil#tcp652</smilref>
<smilref>speechgen0038.smil#tcp654</smilref>
<smilref>speechgen0038.smil#tcp655</smilref>
<smilref>speechgen0039.smil#tcp657</smilref>
<smilref>speechgen0039.smil#tcp658</smilref>
<smilref>speechgen0039.smil#tcp659</smilref>
</smilrefs>
<smilrefs id="id612">
<smilref>speechgen0006.smil#tcp65</smilref>
</smilrefs>
<smilrefs id="id613">
<smilref>speechgen0022.smil#tcp390</smilref>
<smilref>speechgen0033.smil#tcp575</smilref>
<smilref>speechgen0034.smil#tcp607</smilref>
</smilrefs>
<smilrefs id="id614">
<smilref>speechgen0010.smil#tcp132</smilref>
<smilref>speechgen0022.smil#tcp371</smilref>
</smilrefs>
<smilrefs id="id615">
<smilref>speechgen0009.smil#tcp125</smilref>
<smilref>speechgen0022.smil#tcp392</smilref>
<smilref>speechgen0028.smil#tcp483</smilref>
<smilref>speechgen0033.smil#tcp583</smilref>
<smilref>speechgen0035.smil#tcp628</smilref>
</smilrefs>
<smilrefs id="id616">
<smilref>speechgen0009.smil#tcp127</smilref>
</smilrefs>
<smilrefs id="id617">
<smilref>speechgen0010.smil#tcp141</smilref>
</smilrefs>
<smilrefs id="id618">
<smilref>speechgen0003.smil#tcp7</smilref>
<smilref>speechgen0003.smil#tcp8</smilref>
<smilref>speechgen0003.smil#tcp9</smilref>
<smilref>speechgen0003.smil#tcp17</smilref>
<smilref>speechgen0004.smil#tcp24</smilref>
<smilref>speechgen0004.smil#tcp47</smilref>
<smilref>speechgen0009.smil#tcp119</smilref>
<smilref>speechgen0009.smil#tcp123</smilref>
<smilref>speechgen0010.smil#tcp136</smilref>
<smilref>speechgen0010.smil#tcp142</smilref>
<smilref>speechgen0012.smil#tcp162</smilref>
<smilref>speechgen0015.smil#tcp203</smilref>
<smilref>speechgen0015.smil#tcp207</smilref>
<smilref>speechgen0018.smil#tcp245</smilref>
<smilref>speechgen0018.smil#tcp248</smilref>
<smilref>speechgen0018.smil#tcp249</smilref>
<smilref>speechgen0018.smil#tcp258</smilref>
<smilref>speechgen0018.smil#tcp259</smilref>
<smilref>speechgen0020.smil#tcs26</smilref>
<smilref>speechgen0022.smil#tcp369</smilref>
<smilref>speechgen0022.smil#tcp389</smilref>
<smilref>speechgen0022.smil#tcp390</smilref>
<smilref>speechgen0034.smil#tcp613</smilref>
<smilref>speechgen0037.smil#tcp637</smilref>
<smilref>speechgen0038.smil#tcp647</smilref>
<smilref>speechgen0038.smil#tcp651</smilref>
</smilrefs>
<smilrefs id="id619">
<smilref>speechgen0010.smil#tcp129</smilref>
</smilrefs>
<smilrefs id="id620">
<smilref>speechgen0003.smil#tcp11</smilref>
<smilref>speechgen0011.smil#tcp149</smilref>
<smilref>speechgen0015.smil#tcp205</smilref>
<smilref>speechgen0018.smil#tcp259</smilref>
<smilref>speechgen0018.smil#tcp268</smilref>
<smilref>speechgen0019.smil#tcp281</smilref>
<smilref>speechgen0019.smil#tcp283</smilref>
<smilref>speechgen0022.smil#tcp376</smilref>
<smilref>speechgen0025.smil#tcp441</smilref>
<smilref>speechgen0028.smil#tcp494</smilref>
<smilref>speechgen0031.smil#tcp544</smilref>
<smilref>speechgen0031.smil#tcp546</smilref>
<smilref>speechgen0033.smil#tcp573</smilref>
<smilref>speechgen0034.smil#tcp605</smilref>
</smilrefs>
<smilrefs id="id621">
<smilref>speechgen0018.smil#tcp253</smilref>
<smilref>speechgen0028.smil#tcp488</smilref>
</smilrefs>
<smilrefs id="id622">
<smilref>speechgen0009.smil#tcp119</smilref>
<smilref>speechgen0010.smil#tcp142</smilref>
<smilref>speechgen0018.smil#tcp271</smilref>
<smilref>speechgen0031.smil#tcp542</smilref>
<smilref>speechgen0031.smil#tcp545</smilref>
</smilrefs>
<smilrefs id="id623">
<smilref>speechgen0010.smil#tcp138</smilref>
<smilref>speechgen0011.smil#tcp151</smilref>
<smilref>speechgen0012.smil#tcp161</smilref>
<smilref>speechgen0013.smil#tcs1</smilref>
<smilref>speechgen0022.smil#tcp372</smilref>
<smilref>speechgen0022.smil#tcp374</smilref>
<smilref>speechgen0022.smil#tcp375</smilref>
<smilref>speechgen0022.smil#tcp376</smilref>
<smilref>speechgen0022.smil#tcp385</smilref>
<smilref>speechgen0022.smil#tcp396</smilref>
<smilref>speechgen0025.smil#tcp443</smilref>
<smilref>speechgen0026.smil#tcs83</smilref>
<smilref>speechgen0032.smil#tcs115</smilref>
<smilref>speechgen0038.smil#tcp644</smilref>
</smilrefs>
<smilrefs id="id624">
<smilref>speechgen0010.smil#tcp137</smilref>
</smilrefs>
<smilrefs id="id625">
<smilref>speechgen0003.smil#tcp6</smilref>
<smilref>speechgen0003.smil#tcp8</smilref>
<smilref>speechgen0003.smil#tcp9</smilref>
<smilref>speechgen0003.smil#tcp10</smilref>
<smilref>speechgen0003.smil#tcp11</smilref>
<smilref>speechgen0003.smil#tcp12</smilref>
<smilref>speechgen0003.smil#tcp13</smilref>
<smilref>speechgen0003.smil#tcp14</smilref>
<smilref>speechgen0003.smil#tcp15</smilref>
<smilref>speechgen0003.smil#tcp16</smilref>
<smilref>speechgen0003.smil#tcp18</smilref>
<smilref>speechgen0003.smil#tcp19</smilref>
<smilref>speechgen0004.smil#tcp26</smilref>
<smilref>speechgen0005.smil#tcp56</smilref>
<smilref>speechgen0005.smil#tcp58</smilref>
<smilref>speechgen0005.smil#tcp60</smilref>
<smilref>speechgen0005.smil#tcp62</smilref>
<smilref>speechgen0005.smil#tcp64</smilref>
<smilref>speechgen0006.smil#tcp72</smilref>
<smilref>speechgen0007.smil#tcp80</smilref>
<smilref>speechgen0008.smil#tcp87</smilref>
<smilref>speechgen0008.smil#tcp89</smilref>
<smilref>speechgen0008.smil#tcp95</smilref>
<smilref>speechgen0008.smil#tcp97</smilref>
<smilref>speechgen0008.smil#tcp99</smilref>
<smilref>speechgen0008.smil#tcp109</smilref>
<smilref>speechgen0008.smil#tcp113</smilref>
<smilref>speechgen0008.smil#tcp115</smilref>
<smilref>speechgen0009.smil#tcp118</smilref>
<smilref>speechgen0009.smil#tcp122</smilref>
<smilref>speechgen0009.smil#tcp126</smilref>
<smilref>speechgen0010.smil#tcp131</smilref>
<smilref>speechgen0010.smil#tcp132</smilref>
<smilref>speechgen0010.smil#tcp138</smilref>
<smilref>speechgen0010.smil#tcp141</smilref>
<smilref>speechgen0011.smil#tcp146</smilref>
<smilref>speechgen0011.smil#tcp150</smilref>
<smilref>speechgen0011.smil#tcp151</smilref>
<smilref>speechgen0011.smil#tcp152</smilref>
<smilref>speechgen0011.smil#tcp153</smilref>
<smilref>speechgen0011.smil#tcp154</smilref>
<smilref>speechgen0011.smil#tcp156</smilref>
<smilref>speechgen0011.smil#tcp157</smilref>
<smilref>speechgen0011.smil#tcp159</smilref>
<smilref>speechgen0012.smil#tcp162</smilref>
<smilref>speechgen0012.smil#tcp163</smilref>
<smilref>speechgen0013.smil#tcs1</smilref>
<smilref>speechgen0015.smil#tcp198</smilref>
<smilref>speechgen0015.smil#tcp199</smilref>
<smilref>speechgen0015.smil#tcp203</smilref>
<smilref>speechgen0015.smil#tcp205</smilref>
<smilref>speechgen0015.smil#tcp207</smilref>
<smilref>speechgen0015.smil#tcp208</smilref>
<smilref>speechgen0016.smil#tcs14</smilref>
<smilref>speechgen0018.smil#tcp237</smilref>
<smilref>speechgen0018.smil#tcp239</smilref>
<smilref>speechgen0018.smil#tcp244</smilref>
<smilref>speechgen0018.smil#tcp248</smilref>
<smilref>speechgen0018.smil#tcp250</smilref>
<smilref>speechgen0018.smil#tcp251</smilref>
<smilref>speechgen0018.smil#tcp252</smilref>
<smilref>speechgen0018.smil#tcp255</smilref>
<smilref>speechgen0018.smil#tcp257</smilref>
<smilref>speechgen0018.smil#tcp261</smilref>
<smilref>speechgen0018.smil#tcp262</smilref>
<smilref>speechgen0018.smil#tcp263</smilref>
<smilref>speechgen0018.smil#tcp264</smilref>
<smilref>speechgen0018.smil#tcp265</smilref>
<smilref>speechgen0018.smil#tcp266</smilref>
<smilref>speechgen0018.smil#tcp267</smilref>
<smilref>speechgen0018.smil#tcp268</smilref>
<smilref>speechgen0018.smil#tcp269</smilref>
<smilref>speechgen0018.smil#tcp270</smilref>
<smilref>speechgen0018.smil#tcp272</smilref>
<smilref>speechgen0019.smil#tcp276</smilref>
<smilref>speechgen0019.smil#tcp278</smilref>
<smilref>speechgen0019.smil#tcp279</smilref>
<smilref>speechgen0019.smil#tcp280</smilref>
<smilref>speechgen0019.smil#tcp281</smilref>
<smilref>speechgen0019.smil#tcp282</smilref>
<smilref>speechgen0019.smil#tcp284</smilref>
<smilref>speechgen0019.smil#tcp285</smilref>
<smilref>speechgen0020.smil#tcs26</smilref>
<smilref>speechgen0022.smil#tcp366</smilref>
<smilref>speechgen0022.smil#tcp368</smilref>
<smilref>speechgen0022.smil#tcp369</smilref>
<smilref>speechgen0022.smil#tcp370</smilref>
<smilref>speechgen0022.smil#tcp371</smilref>
<smilref>speechgen0022.smil#tcp373</smilref>
<smilref>speechgen0022.smil#tcp375</smilref>
<smilref>speechgen0022.smil#tcp376</smilref>
<smilref>speechgen0022.smil#tcp377</smilref>
<smilref>speechgen0022.smil#tcp378</smilref>
<smilref>speechgen0022.smil#tcp383</smilref>
<smilref>speechgen0022.smil#tcp384</smilref>
<smilref>speechgen0022.smil#tcp385</smilref>
<smilref>speechgen0022.smil#tcp387</smilref>
<smilref>speechgen0022.smil#tcp388</smilref>
<smilref>speechgen0022.smil#tcp390</smilref>
<smilref>speechgen0022.smil#tcp394</smilref>
<smilref>speechgen0022.smil#tcp395</smilref>
<smilref>speechgen0022.smil#tcp398</smilref>
<smilref>speechgen0023.smil#tcs64</smilref>
<smilref>speechgen0025.smil#tcp441</smilref>
<smilref>speechgen0025.smil#tcp442</smilref>
<smilref>speechgen0025.smil#tcp443</smilref>
<smilref>speechgen0025.smil#tcp445</smilref>
<smilref>speechgen0025.smil#tcp446</smilref>
<smilref>speechgen0025.smil#tcp448</smilref>
<smilref>speechgen0025.smil#tcp449</smilref>
<smilref>speechgen0025.smil#tcp451</smilref>
<smilref>speechgen0026.smil#tcs83</smilref>
<smilref>speechgen0028.smil#tcp481</smilref>
<smilref>speechgen0028.smil#tcp486</smilref>
<smilref>speechgen0028.smil#tcp491</smilref>
<smilref>speechgen0028.smil#tcp492</smilref>
<smilref>speechgen0028.smil#tcp494</smilref>
<smilref>speechgen0028.smil#tcp495</smilref>
<smilref>speechgen0028.smil#tcp496</smilref>
<smilref>speechgen0028.smil#tcp497</smilref>
<smilref>speechgen0028.smil#tcp499</smilref>
<smilref>speechgen0029.smil#tcs96</smilref>
<smilref>speechgen0031.smil#tcp542</smilref>
<smilref>speechgen0031.smil#tcp543</smilref>
<smilref>speechgen0031.smil#tcp544</smilref>
<smilref>speechgen0031.smil#tcp546</smilref>
<smilref>speechgen0032.smil#tcs115</smilref>
<smilref>speechgen0033.smil#tcp572</smilref>
<smilref>speechgen0033.smil#tcp573</smilref>
<smilref>speechgen0033.smil#tcp574</smilref>
<smilref>speechgen0033.smil#tcp575</smilref>
<smilref>speechgen0033.smil#tcp576</smilref>
<smilref>speechgen0033.smil#tcp577</smilref>
<smilref>speechgen0033.smil#tcp579</smilref>
<smilref>speechgen0033.smil#tcp580</smilref>
<smilref>speechgen0033.smil#tcp581</smilref>
<smilref>speechgen0033.smil#tcp585</smilref>
<smilref>speechgen0033.smil#tcp587</smilref>
<smilref>speechgen0033.smil#tcp589</smilref>
<smilref>speechgen0033.smil#tcp590</smilref>
<smilref>speechgen0033.smil#tcp596</smilref>
<smilref>speechgen0033.smil#tcp598</smilref>
<smilref>speechgen0033.smil#tcp599</smilref>
<smilref>speechgen0033.smil#tcp600</smilref>
<smilref>speechgen0034.smil#tcp603</smilref>
<smilref>speechgen0034.smil#tcp604</smilref>
<smilref>speechgen0034.smil#tcp605</smilref>
<smilref>speechgen0034.smil#tcp606</smilref>
<smilref>speechgen0034.smil#tcp607</smilref>
<smilref>speechgen0034.smil#tcp608</smilref>
<smilref>speechgen0034.smil#tcp609</smilref>
<smilref>speechgen0034.smil#tcp612</smilref>
<smilref>speechgen0034.smil#tcp615</smilref>
<smilref>speechgen0034.smil#tcp618</smilref>
<smilref>speechgen0034.smil#tcp620</smilref>
<smilref>speechgen0034.smil#tcp622</smilref>
<smilref>speechgen0034.smil#tcp625</smilref>
<smilref>speechgen0035.smil#tcp627</smilref>
<smilref>speechgen0035.smil#tcp630</smilref>
<smilref>speechgen0035.smil#tcp631</smilref>
<smilref>speechgen0035.smil#tcp632</smilref>
<smilref>speechgen0037.smil#tcp636</smilref>
<smilref>speechgen0037.smil#tcp637</smilref>
<smilref>speechgen0037.smil#tcp639</smilref>
<smilref>speechgen0038.smil#tcp642</smilref>
<smilref>speechgen0038.smil#tcp643</smilref>
<smilref>speechgen0038.smil#tcp646</smilref>
<smilref>speechgen0038.smil#tcp647</smilref>
<smilref>speechgen0038.smil#tcp649</smilref>
<smilref>speechgen0038.smil#tcp651</smilref>
<smilref>speechgen0038.smil#tcp654</smilref>
<smilref>speechgen0039.smil#tcp657</smilref>
<smilref>speechgen0039.smil#tcp659</smilref>
</smilrefs>
<smilrefs id="id626">
<smilref>speechgen0022.smil#tcp369</smilref>
</smilrefs>
<smilrefs id="id627">
<smilref>speechgen0018.smil#tcp259</smilref>
</smilrefs>
<smilrefs id="id628">
<smilref>speechgen0015.smil#tcp203</smilref>
<smilref>speechgen0035.smil#tcp627</smilref>
</smilrefs>
<smilrefs id="id629">
<smilref>speechgen0015.smil#tcp202</smilref>
<smilref>speechgen0015.smil#tcp207</smilref>
<smilref>speechgen0016.smil#tcs14</smilref>
<smilref>speechgen0018.smil#tcp240</smilref>
<smilref>speechgen0028.smil#tcp499</smilref>
</smilrefs>
<smilrefs id="id630">
<smilref>speechgen0003.smil#tcp10</smilref>
</smilrefs>
<smilrefs id="id631">
<smilref>speechgen0033.smil#tcp580</smilref>
</smilrefs>
<smilrefs id="id632">
<smilref>speechgen0003.smil#tcp14</smilref>
<smilref>speechgen0003.smil#tcp15</smilref>
<smilref>speechgen0008.smil#tcp101</smilref>
<smilref>speechgen0018.smil#tcp269</smilref>
<smilref>speechgen0018.smil#tcp272</smilref>
<smilref>speechgen0019.smil#tcp280</smilref>
<smilref>speechgen0020.smil#tcs26</smilref>
<smilref>speechgen0033.smil#tcp581</smilref>
<smilref>speechgen0033.smil#tcp584</smilref>
<smilref>speechgen0033.smil#tcp586</smilref>
<smilref>speechgen0034.smil#tcp613</smilref>
<smilref>speechgen0034.smil#tcp615</smilref>
<smilref>speechgen0034.smil#tcp624</smilref>
</smilrefs>
<smilrefs id="id633">
<smilref>speechgen0018.smil#tcp244</smilref>
<smilref>speechgen0018.smil#tcp263</smilref>
</smilrefs>
<smilrefs id="id634">
<smilref>speechgen0008.smil#tcp105</smilref>
<smilref>speechgen0008.smil#tcp107</smilref>
<smilref>speechgen0015.smil#tcp206</smilref>
<smilref>speechgen0016.smil#tcs14</smilref>
<smilref>speechgen0026.smil#tcs83</smilref>
<smilref>speechgen0032.smil#tcs115</smilref>
</smilrefs>
<smilrefs id="id635">
<smilref>speechgen0001.smil#tcp1</smilref>
<smilref>speechgen0002.smil#tcp3</smilref>
<smilref>speechgen0003.smil#tcp8</smilref>
<smilref>speechgen0003.smil#tcp9</smilref>
<smilref>speechgen0003.smil#tcp10</smilref>
<smilref>speechgen0004.smil#tcp47</smilref>
<smilref>speechgen0020.smil#tcs26</smilref>
</smilrefs>
<smilrefs id="id636">
<smilref>speechgen0009.smil#tcp118</smilref>
<smilref>speechgen0018.smil#tcp254</smilref>
<smilref>speechgen0028.smil#tcp482</smilref>
<smilref>speechgen0028.smil#tcp483</smilref>
</smilrefs>
<smilrefs id="id637">
<smilref>speechgen0022.smil#tcp396</smilref>
<smilref>speechgen0038.smil#tcp644</smilref>
</smilrefs>
<smilrefs id="id638">
<smilref>speechgen0028.smil#tcp482</smilref>
<smilref>speechgen0028.smil#tcp488</smilref>
<smilref>speechgen0028.smil#tcp491</smilref>
<smilref>speechgen0028.smil#tcp492</smilref>
<smilref>speechgen0033.smil#tcp600</smilref>
<smilref>speechgen0037.smil#tcp638</smilref>
<smilref>speechgen0039.smil#tcp657</smilref>
</smilrefs>
<smilrefs id="id639">
<smilref>speechgen0022.smil#tcp380</smilref>
<smilref>speechgen0028.smil#tcp486</smilref>
</smilrefs>
<smilrefs id="id640">
<smilref>speechgen0028.smil#tcp483</smilref>
</smilrefs>
</search>
